{
    "stat_per_model": {
        "meta-llama/Llama-3-8b-chat-hf": {
            "injection_successful_count": 88.0,
            "injection_unsuccessful_count": 163.0,
            "total_count": 251.0,
            "injection_successful_percentage": 0.350597609561753,
            "injection_unsuccessful_percentage": 0.649402390438247
        },
        "meta-llama/Llama-3-70b-chat-hf": {
            "injection_successful_count": 78.0,
            "injection_unsuccessful_count": 173.0,
            "total_count": 251.0,
            "injection_successful_percentage": 0.3107569721115538,
            "injection_unsuccessful_percentage": 0.6892430278884463
        },
        "mistralai/Mistral-7B-Instruct-v0.2": {
            "injection_successful_count": 108.0,
            "injection_unsuccessful_count": 143.0,
            "total_count": 251.0,
            "injection_successful_percentage": 0.4302788844621514,
            "injection_unsuccessful_percentage": 0.5697211155378487
        },
        "mistralai/Mixtral-8x22B-Instruct-v0.1": {
            "injection_successful_count": 90.0,
            "injection_unsuccessful_count": 161.0,
            "total_count": 251.0,
            "injection_successful_percentage": 0.35856573705179284,
            "injection_unsuccessful_percentage": 0.6414342629482072
        }
    },
    "stat_per_model_per_variant": {
        "meta-llama/Llama-3-8b-chat-hf": {
            "ignore_previous_instructions": {
                "injection_successful_count": 11,
                "injection_unsuccessful_count": 14,
                "total_count": 25,
                "injection_successful_percentage": 0.44,
                "injection_unsuccessful_percentage": 0.56
            },
            "indirect_reference": {
                "injection_successful_count": 6,
                "injection_unsuccessful_count": 7,
                "total_count": 13,
                "injection_successful_percentage": 0.46153846153846156,
                "injection_unsuccessful_percentage": 0.5384615384615384
            },
            "token_smuggling": {
                "injection_successful_count": 0,
                "injection_unsuccessful_count": 13,
                "total_count": 13,
                "injection_successful_percentage": 0.0,
                "injection_unsuccessful_percentage": 1.0
            },
            "system_mode": {
                "injection_successful_count": 4,
                "injection_unsuccessful_count": 15,
                "total_count": 19,
                "injection_successful_percentage": 0.21052631578947367,
                "injection_unsuccessful_percentage": 0.7894736842105263
            },
            "different_user_input_language": {
                "injection_successful_count": 17,
                "injection_unsuccessful_count": 8,
                "total_count": 25,
                "injection_successful_percentage": 0.68,
                "injection_unsuccessful_percentage": 0.32
            },
            "overload_with_information": {
                "injection_successful_count": 5,
                "injection_unsuccessful_count": 15,
                "total_count": 20,
                "injection_successful_percentage": 0.25,
                "injection_unsuccessful_percentage": 0.75
            },
            "few_shot_attack": {
                "injection_successful_count": 4,
                "injection_unsuccessful_count": 7,
                "total_count": 11,
                "injection_successful_percentage": 0.36363636363636365,
                "injection_unsuccessful_percentage": 0.6363636363636364
            },
            "mixed_techniques": {
                "injection_successful_count": 9,
                "injection_unsuccessful_count": 24,
                "total_count": 33,
                "injection_successful_percentage": 0.2727272727272727,
                "injection_unsuccessful_percentage": 0.7272727272727273
            },
            "many_shot_attack": {
                "injection_successful_count": 1,
                "injection_unsuccessful_count": 6,
                "total_count": 7,
                "injection_successful_percentage": 0.14285714285714285,
                "injection_unsuccessful_percentage": 0.8571428571428571
            },
            "repeated_token_attack": {
                "injection_successful_count": 2,
                "injection_unsuccessful_count": 4,
                "total_count": 6,
                "injection_successful_percentage": 0.3333333333333333,
                "injection_unsuccessful_percentage": 0.6666666666666666
            },
            "persuasion": {
                "injection_successful_count": 7,
                "injection_unsuccessful_count": 19,
                "total_count": 26,
                "injection_successful_percentage": 0.2692307692307692,
                "injection_unsuccessful_percentage": 0.7307692307692307
            },
            "payload_splitting": {
                "injection_successful_count": 2,
                "injection_unsuccessful_count": 7,
                "total_count": 9,
                "injection_successful_percentage": 0.2222222222222222,
                "injection_unsuccessful_percentage": 0.7777777777777778
            },
            "output_formatting_manipulation": {
                "injection_successful_count": 11,
                "injection_unsuccessful_count": 6,
                "total_count": 17,
                "injection_successful_percentage": 0.6470588235294118,
                "injection_unsuccessful_percentage": 0.35294117647058826
            },
            "hypothetical_scenario": {
                "injection_successful_count": 4,
                "injection_unsuccessful_count": 9,
                "total_count": 13,
                "injection_successful_percentage": 0.3076923076923077,
                "injection_unsuccessful_percentage": 0.6923076923076923
            },
            "virtualization": {
                "injection_successful_count": 5,
                "injection_unsuccessful_count": 9,
                "total_count": 14,
                "injection_successful_percentage": 0.35714285714285715,
                "injection_unsuccessful_percentage": 0.6428571428571429
            }
        },
        "meta-llama/Llama-3-70b-chat-hf": {
            "ignore_previous_instructions": {
                "injection_successful_count": 16,
                "injection_unsuccessful_count": 9,
                "total_count": 25,
                "injection_successful_percentage": 0.64,
                "injection_unsuccessful_percentage": 0.36
            },
            "indirect_reference": {
                "injection_successful_count": 2,
                "injection_unsuccessful_count": 11,
                "total_count": 13,
                "injection_successful_percentage": 0.15384615384615385,
                "injection_unsuccessful_percentage": 0.8461538461538461
            },
            "token_smuggling": {
                "injection_successful_count": 1,
                "injection_unsuccessful_count": 12,
                "total_count": 13,
                "injection_successful_percentage": 0.07692307692307693,
                "injection_unsuccessful_percentage": 0.9230769230769231
            },
            "system_mode": {
                "injection_successful_count": 7,
                "injection_unsuccessful_count": 12,
                "total_count": 19,
                "injection_successful_percentage": 0.3684210526315789,
                "injection_unsuccessful_percentage": 0.631578947368421
            },
            "different_user_input_language": {
                "injection_successful_count": 7,
                "injection_unsuccessful_count": 18,
                "total_count": 25,
                "injection_successful_percentage": 0.28,
                "injection_unsuccessful_percentage": 0.72
            },
            "overload_with_information": {
                "injection_successful_count": 5,
                "injection_unsuccessful_count": 15,
                "total_count": 20,
                "injection_successful_percentage": 0.25,
                "injection_unsuccessful_percentage": 0.75
            },
            "few_shot_attack": {
                "injection_successful_count": 3,
                "injection_unsuccessful_count": 8,
                "total_count": 11,
                "injection_successful_percentage": 0.2727272727272727,
                "injection_unsuccessful_percentage": 0.7272727272727273
            },
            "mixed_techniques": {
                "injection_successful_count": 9,
                "injection_unsuccessful_count": 24,
                "total_count": 33,
                "injection_successful_percentage": 0.2727272727272727,
                "injection_unsuccessful_percentage": 0.7272727272727273
            },
            "many_shot_attack": {
                "injection_successful_count": 3,
                "injection_unsuccessful_count": 4,
                "total_count": 7,
                "injection_successful_percentage": 0.42857142857142855,
                "injection_unsuccessful_percentage": 0.5714285714285714
            },
            "repeated_token_attack": {
                "injection_successful_count": 2,
                "injection_unsuccessful_count": 4,
                "total_count": 6,
                "injection_successful_percentage": 0.3333333333333333,
                "injection_unsuccessful_percentage": 0.6666666666666666
            },
            "persuasion": {
                "injection_successful_count": 6,
                "injection_unsuccessful_count": 20,
                "total_count": 26,
                "injection_successful_percentage": 0.23076923076923078,
                "injection_unsuccessful_percentage": 0.7692307692307693
            },
            "payload_splitting": {
                "injection_successful_count": 1,
                "injection_unsuccessful_count": 8,
                "total_count": 9,
                "injection_successful_percentage": 0.1111111111111111,
                "injection_unsuccessful_percentage": 0.8888888888888888
            },
            "output_formatting_manipulation": {
                "injection_successful_count": 9,
                "injection_unsuccessful_count": 8,
                "total_count": 17,
                "injection_successful_percentage": 0.5294117647058824,
                "injection_unsuccessful_percentage": 0.47058823529411764
            },
            "hypothetical_scenario": {
                "injection_successful_count": 2,
                "injection_unsuccessful_count": 11,
                "total_count": 13,
                "injection_successful_percentage": 0.15384615384615385,
                "injection_unsuccessful_percentage": 0.8461538461538461
            },
            "virtualization": {
                "injection_successful_count": 5,
                "injection_unsuccessful_count": 9,
                "total_count": 14,
                "injection_successful_percentage": 0.35714285714285715,
                "injection_unsuccessful_percentage": 0.6428571428571429
            }
        },
        "mistralai/Mistral-7B-Instruct-v0.2": {
            "ignore_previous_instructions": {
                "injection_successful_count": 9,
                "injection_unsuccessful_count": 16,
                "total_count": 25,
                "injection_successful_percentage": 0.36,
                "injection_unsuccessful_percentage": 0.64
            },
            "indirect_reference": {
                "injection_successful_count": 5,
                "injection_unsuccessful_count": 8,
                "total_count": 13,
                "injection_successful_percentage": 0.38461538461538464,
                "injection_unsuccessful_percentage": 0.6153846153846154
            },
            "token_smuggling": {
                "injection_successful_count": 0,
                "injection_unsuccessful_count": 13,
                "total_count": 13,
                "injection_successful_percentage": 0.0,
                "injection_unsuccessful_percentage": 1.0
            },
            "system_mode": {
                "injection_successful_count": 7,
                "injection_unsuccessful_count": 12,
                "total_count": 19,
                "injection_successful_percentage": 0.3684210526315789,
                "injection_unsuccessful_percentage": 0.631578947368421
            },
            "different_user_input_language": {
                "injection_successful_count": 12,
                "injection_unsuccessful_count": 13,
                "total_count": 25,
                "injection_successful_percentage": 0.48,
                "injection_unsuccessful_percentage": 0.52
            },
            "overload_with_information": {
                "injection_successful_count": 7,
                "injection_unsuccessful_count": 13,
                "total_count": 20,
                "injection_successful_percentage": 0.35,
                "injection_unsuccessful_percentage": 0.65
            },
            "few_shot_attack": {
                "injection_successful_count": 6,
                "injection_unsuccessful_count": 5,
                "total_count": 11,
                "injection_successful_percentage": 0.5454545454545454,
                "injection_unsuccessful_percentage": 0.45454545454545453
            },
            "mixed_techniques": {
                "injection_successful_count": 16,
                "injection_unsuccessful_count": 17,
                "total_count": 33,
                "injection_successful_percentage": 0.48484848484848486,
                "injection_unsuccessful_percentage": 0.5151515151515151
            },
            "many_shot_attack": {
                "injection_successful_count": 5,
                "injection_unsuccessful_count": 2,
                "total_count": 7,
                "injection_successful_percentage": 0.7142857142857143,
                "injection_unsuccessful_percentage": 0.2857142857142857
            },
            "repeated_token_attack": {
                "injection_successful_count": 5,
                "injection_unsuccessful_count": 1,
                "total_count": 6,
                "injection_successful_percentage": 0.8333333333333334,
                "injection_unsuccessful_percentage": 0.16666666666666666
            },
            "persuasion": {
                "injection_successful_count": 15,
                "injection_unsuccessful_count": 11,
                "total_count": 26,
                "injection_successful_percentage": 0.5769230769230769,
                "injection_unsuccessful_percentage": 0.4230769230769231
            },
            "payload_splitting": {
                "injection_successful_count": 2,
                "injection_unsuccessful_count": 7,
                "total_count": 9,
                "injection_successful_percentage": 0.2222222222222222,
                "injection_unsuccessful_percentage": 0.7777777777777778
            },
            "output_formatting_manipulation": {
                "injection_successful_count": 9,
                "injection_unsuccessful_count": 8,
                "total_count": 17,
                "injection_successful_percentage": 0.5294117647058824,
                "injection_unsuccessful_percentage": 0.47058823529411764
            },
            "hypothetical_scenario": {
                "injection_successful_count": 4,
                "injection_unsuccessful_count": 9,
                "total_count": 13,
                "injection_successful_percentage": 0.3076923076923077,
                "injection_unsuccessful_percentage": 0.6923076923076923
            },
            "virtualization": {
                "injection_successful_count": 6,
                "injection_unsuccessful_count": 8,
                "total_count": 14,
                "injection_successful_percentage": 0.42857142857142855,
                "injection_unsuccessful_percentage": 0.5714285714285714
            }
        },
        "mistralai/Mixtral-8x22B-Instruct-v0.1": {
            "ignore_previous_instructions": {
                "injection_successful_count": 11,
                "injection_unsuccessful_count": 14,
                "total_count": 25,
                "injection_successful_percentage": 0.44,
                "injection_unsuccessful_percentage": 0.56
            },
            "indirect_reference": {
                "injection_successful_count": 6,
                "injection_unsuccessful_count": 7,
                "total_count": 13,
                "injection_successful_percentage": 0.46153846153846156,
                "injection_unsuccessful_percentage": 0.5384615384615384
            },
            "token_smuggling": {
                "injection_successful_count": 1,
                "injection_unsuccessful_count": 12,
                "total_count": 13,
                "injection_successful_percentage": 0.07692307692307693,
                "injection_unsuccessful_percentage": 0.9230769230769231
            },
            "system_mode": {
                "injection_successful_count": 3,
                "injection_unsuccessful_count": 16,
                "total_count": 19,
                "injection_successful_percentage": 0.15789473684210525,
                "injection_unsuccessful_percentage": 0.8421052631578947
            },
            "different_user_input_language": {
                "injection_successful_count": 18,
                "injection_unsuccessful_count": 7,
                "total_count": 25,
                "injection_successful_percentage": 0.72,
                "injection_unsuccessful_percentage": 0.28
            },
            "overload_with_information": {
                "injection_successful_count": 7,
                "injection_unsuccessful_count": 13,
                "total_count": 20,
                "injection_successful_percentage": 0.35,
                "injection_unsuccessful_percentage": 0.65
            },
            "few_shot_attack": {
                "injection_successful_count": 1,
                "injection_unsuccessful_count": 10,
                "total_count": 11,
                "injection_successful_percentage": 0.09090909090909091,
                "injection_unsuccessful_percentage": 0.9090909090909091
            },
            "mixed_techniques": {
                "injection_successful_count": 12,
                "injection_unsuccessful_count": 21,
                "total_count": 33,
                "injection_successful_percentage": 0.36363636363636365,
                "injection_unsuccessful_percentage": 0.6363636363636364
            },
            "many_shot_attack": {
                "injection_successful_count": 4,
                "injection_unsuccessful_count": 3,
                "total_count": 7,
                "injection_successful_percentage": 0.5714285714285714,
                "injection_unsuccessful_percentage": 0.42857142857142855
            },
            "repeated_token_attack": {
                "injection_successful_count": 2,
                "injection_unsuccessful_count": 4,
                "total_count": 6,
                "injection_successful_percentage": 0.3333333333333333,
                "injection_unsuccessful_percentage": 0.6666666666666666
            },
            "persuasion": {
                "injection_successful_count": 5,
                "injection_unsuccessful_count": 21,
                "total_count": 26,
                "injection_successful_percentage": 0.19230769230769232,
                "injection_unsuccessful_percentage": 0.8076923076923077
            },
            "payload_splitting": {
                "injection_successful_count": 2,
                "injection_unsuccessful_count": 7,
                "total_count": 9,
                "injection_successful_percentage": 0.2222222222222222,
                "injection_unsuccessful_percentage": 0.7777777777777778
            },
            "output_formatting_manipulation": {
                "injection_successful_count": 12,
                "injection_unsuccessful_count": 5,
                "total_count": 17,
                "injection_successful_percentage": 0.7058823529411765,
                "injection_unsuccessful_percentage": 0.29411764705882354
            },
            "hypothetical_scenario": {
                "injection_successful_count": 2,
                "injection_unsuccessful_count": 11,
                "total_count": 13,
                "injection_successful_percentage": 0.15384615384615385,
                "injection_unsuccessful_percentage": 0.8461538461538461
            },
            "virtualization": {
                "injection_successful_count": 4,
                "injection_unsuccessful_count": 10,
                "total_count": 14,
                "injection_successful_percentage": 0.2857142857142857,
                "injection_unsuccessful_percentage": 0.7142857142857143
            }
        }
    },
    "stat_per_model_per_type": {
        "meta-llama/Llama-3-8b-chat-hf": {
            "direct": {
                "injection_successful_count": 62,
                "injection_unsuccessful_count": 134,
                "total_count": 196,
                "injection_successful_percentage": 0.3163265306122449,
                "injection_unsuccessful_percentage": 0.6836734693877551
            },
            "indirect": {
                "injection_successful_count": 26,
                "injection_unsuccessful_count": 29,
                "total_count": 55,
                "injection_successful_percentage": 0.4727272727272727,
                "injection_unsuccessful_percentage": 0.5272727272727272
            }
        },
        "meta-llama/Llama-3-70b-chat-hf": {
            "direct": {
                "injection_successful_count": 55,
                "injection_unsuccessful_count": 141,
                "total_count": 196,
                "injection_successful_percentage": 0.28061224489795916,
                "injection_unsuccessful_percentage": 0.7193877551020408
            },
            "indirect": {
                "injection_successful_count": 23,
                "injection_unsuccessful_count": 32,
                "total_count": 55,
                "injection_successful_percentage": 0.41818181818181815,
                "injection_unsuccessful_percentage": 0.5818181818181818
            }
        },
        "mistralai/Mistral-7B-Instruct-v0.2": {
            "direct": {
                "injection_successful_count": 96,
                "injection_unsuccessful_count": 100,
                "total_count": 196,
                "injection_successful_percentage": 0.4897959183673469,
                "injection_unsuccessful_percentage": 0.5102040816326531
            },
            "indirect": {
                "injection_successful_count": 12,
                "injection_unsuccessful_count": 43,
                "total_count": 55,
                "injection_successful_percentage": 0.21818181818181817,
                "injection_unsuccessful_percentage": 0.7818181818181819
            }
        },
        "mistralai/Mixtral-8x22B-Instruct-v0.1": {
            "direct": {
                "injection_successful_count": 69,
                "injection_unsuccessful_count": 127,
                "total_count": 196,
                "injection_successful_percentage": 0.3520408163265306,
                "injection_unsuccessful_percentage": 0.6479591836734694
            },
            "indirect": {
                "injection_successful_count": 21,
                "injection_unsuccessful_count": 34,
                "total_count": 55,
                "injection_successful_percentage": 0.38181818181818183,
                "injection_unsuccessful_percentage": 0.6181818181818182
            }
        }
    },
    "stat_per_model_per_risk_category": {
        "meta-llama/Llama-3-8b-chat-hf": {
            "security-violating": {
                "injection_successful_count": 70,
                "injection_unsuccessful_count": 110,
                "total_count": 180,
                "injection_successful_percentage": 0.3888888888888889,
                "injection_unsuccessful_percentage": 0.6111111111111112
            },
            "logic-violating": {
                "injection_successful_count": 18,
                "injection_unsuccessful_count": 53,
                "total_count": 71,
                "injection_successful_percentage": 0.2535211267605634,
                "injection_unsuccessful_percentage": 0.7464788732394366
            }
        },
        "meta-llama/Llama-3-70b-chat-hf": {
            "security-violating": {
                "injection_successful_count": 72,
                "injection_unsuccessful_count": 108,
                "total_count": 180,
                "injection_successful_percentage": 0.4,
                "injection_unsuccessful_percentage": 0.6
            },
            "logic-violating": {
                "injection_successful_count": 6,
                "injection_unsuccessful_count": 65,
                "total_count": 71,
                "injection_successful_percentage": 0.08450704225352113,
                "injection_unsuccessful_percentage": 0.9154929577464789
            }
        },
        "mistralai/Mistral-7B-Instruct-v0.2": {
            "security-violating": {
                "injection_successful_count": 83,
                "injection_unsuccessful_count": 97,
                "total_count": 180,
                "injection_successful_percentage": 0.46111111111111114,
                "injection_unsuccessful_percentage": 0.5388888888888889
            },
            "logic-violating": {
                "injection_successful_count": 25,
                "injection_unsuccessful_count": 46,
                "total_count": 71,
                "injection_successful_percentage": 0.352112676056338,
                "injection_unsuccessful_percentage": 0.647887323943662
            }
        },
        "mistralai/Mixtral-8x22B-Instruct-v0.1": {
            "security-violating": {
                "injection_successful_count": 64,
                "injection_unsuccessful_count": 116,
                "total_count": 180,
                "injection_successful_percentage": 0.35555555555555557,
                "injection_unsuccessful_percentage": 0.6444444444444445
            },
            "logic-violating": {
                "injection_successful_count": 26,
                "injection_unsuccessful_count": 45,
                "total_count": 71,
                "injection_successful_percentage": 0.36619718309859156,
                "injection_unsuccessful_percentage": 0.6338028169014085
            }
        }
    }
}